xor_decrypt.v
// XOR Decryption Module
// Decrypts 8-bit ciphertext using same 8-bit key
module xor_decrypt(
    input  [7:0] ciphertext,
    input  [7:0] key,
    output [7:0] plaintext
);
    assign plaintext = ciphertext ^ key;
endmodule

xor_encrypt.v
// XOR Encryption Module
// Encrypts 8-bit plaintext using 8-bit key
module xor_encrypt(
    input  [7:0] plaintext,
    input  [7:0] key,
    output [7:0] ciphertext
);
    assign ciphertext = plaintext ^ key;
endmodule

key_register.v
// Key Register Module
// Stores and manages the secret encryption key
module key_register(
    input clk, reset,
    input load,
    input  [7:0] key_in,
    output reg [7:0] key_out
);
    always @(posedge clk or posedge reset) begin
        if(reset)
            key_out <= 8'b00000000;
        else if(load)
            key_out <= key_in;
    end
endmodule

encryption_top.v
// Top Level - VLSI XOR Encryption System
`include "xor_encrypt.v"
`include "xor_decrypt.v"
`include "key_register.v"

module encryption_top(
    input clk, reset,
    input load_key,
    input  [7:0] plaintext,
    input  [7:0] key_in,
    output [7:0] ciphertext,
    output [7:0] decrypted
);
    wire [7:0] key;

    // Key Register
    key_register KR (
        .clk(clk),
        .reset(reset),
        .load(load_key),
        .key_in(key_in),
        .key_out(key)
    );

    // Encryption
    xor_encrypt ENC (
        .plaintext(plaintext),
        .key(key),
        .ciphertext(ciphertext)
    );

    // Decryption
    xor_decrypt DEC (
        .ciphertext(ciphertext),
        .key(key),
        .plaintext(decrypted)
    );

endmodule

encryption_tb.v
`timescale 1ns/1ns

module encryption_tb;

    reg clk, reset, load_key;
    reg [7:0] plaintext, key_in;
    wire [7:0] ciphertext, decrypted;

    // Instantiate top level
    encryption_top DUT (
        .clk(clk),
        .reset(reset),
        .load_key(load_key),
        .plaintext(plaintext),
        .key_in(key_in),
        .ciphertext(ciphertext),
        .decrypted(decrypted)
    );

    always #5 clk = ~clk;

    initial begin
        $dumpfile("encryption.vcd");
        $dumpvars(0, encryption_tb);

        clk = 0; reset = 1; load_key = 0;
        plaintext = 8'b0; key_in = 8'b0;
        #10 reset = 0;

        $display("=== VLSI XOR Encryption System ===");
        $display("Plaintext  | Key       | Ciphertext | Decrypted | Match?");
        $display("----------------------------------------------------------");

        // Test 1: key = 10101010
        key_in = 8'b10101010; load_key = 1; #10; load_key = 0;
        plaintext = 8'b11001100; #10;
        $display("%b  | %b | %b  | %b  | %s",
            plaintext, key_in, ciphertext, decrypted,
            (plaintext == decrypted) ? "PASS" : "FAIL");

        // Test 2: key = 11110000
        key_in = 8'b11110000; load_key = 1; #10; load_key = 0;
        plaintext = 8'b10101010; #10;
        $display("%b  | %b | %b  | %b  | %s",
            plaintext, key_in, ciphertext, decrypted,
            (plaintext == decrypted) ? "PASS" : "FAIL");

        // Test 3: key = 01010101
        key_in = 8'b01010101; load_key = 1; #10; load_key = 0;
        plaintext = 8'b11111111; #10;
        $display("%b  | %b | %b  | %b  | %s",
            plaintext, key_in, ciphertext, decrypted,
            (plaintext == decrypted) ? "PASS" : "FAIL");

        // Test 4: key = 11001100
        key_in = 8'b11001100; load_key = 1; #10; load_key = 0;
        plaintext = 8'b00110011; #10;
        $display("%b  | %b | %b  | %b  | %s",
            plaintext, key_in, ciphertext, decrypted,
            (plaintext == decrypted) ? "PASS" : "FAIL");

        // Test 5: all zeros key
        key_in = 8'b00000000; load_key = 1; #10; load_key = 0;
        plaintext = 8'b10110110; #10;
        $display("%b  | %b | %b  | %b  | %s",
            plaintext, key_in, ciphertext, decrypted,
            (plaintext == decrypted) ? "PASS" : "FAIL");

        // Test 6: all ones key
        key_in = 8'b11111111; load_key = 1; #10; load_key = 0;
        plaintext = 8'b10110110; #10;
        $display("%b  | %b | %b  | %b  | %s",
            plaintext, key_in, ciphertext, decrypted,
            (plaintext == decrypted) ? "PASS" : "FAIL");

        $display("=== Simulation Complete ===");
        $finish;
    end

endmodule

encryption.vcd
$date
	Fri Apr 24 19:30:33 2026
$end
$version
	Icarus Verilog
$end
$timescale
	1ns
$end
$scope module encryption_tb $end
$var wire 8 ! decrypted [7:0] $end
$var wire 8 " ciphertext [7:0] $end
$var reg 1 # clk $end
$var reg 8 $ key_in [7:0] $end
$var reg 1 % load_key $end
$var reg 8 & plaintext [7:0] $end
$var reg 1 ' reset $end
$scope module DUT $end
$var wire 1 # clk $end
$var wire 8 ( key_in [7:0] $end
$var wire 1 % load_key $end
$var wire 8 ) plaintext [7:0] $end
$var wire 1 ' reset $end
$var wire 8 * key [7:0] $end
$var wire 8 + decrypted [7:0] $end
$var wire 8 , ciphertext [7:0] $end
$scope module DEC $end
$var wire 8 - plaintext [7:0] $end
$var wire 8 . key [7:0] $end
$var wire 8 / ciphertext [7:0] $end
$upscope $end
$scope module ENC $end
$var wire 8 0 ciphertext [7:0] $end
$var wire 8 1 plaintext [7:0] $end
$var wire 8 2 key [7:0] $end
$upscope $end
$scope module KR $end
$var wire 1 # clk $end
$var wire 8 3 key_in [7:0] $end
$var wire 1 % load $end
$var wire 1 ' reset $end
$var reg 8 4 key_out [7:0] $end
$upscope $end
$upscope $end
$upscope $end
$enddefinitions $end
$comment Show the parameter values. $end
$dumpall
$end
#0
$dumpvars
b0 4
b0 3
b0 2
b0 1
b0 0
b0 /
b0 .
b0 -
b0 ,
b0 +
b0 *
b0 )
b0 (
1'
b0 &
0%
b0 $
0#
b0 "
b0 !
$end
#5
1#
#10
0#
1%
b10101010 $
b10101010 (
b10101010 3
0'
#15
b10101010 "
b10101010 ,
b10101010 /
b10101010 0
b0 !
b0 +
b0 -
b10101010 *
b10101010 .
b10101010 2
b10101010 4
1#
#20
b11001100 !
b11001100 +
b11001100 -
b1100110 "
b1100110 ,
b1100110 /
b1100110 0
0#
b11001100 &
b11001100 )
b11001100 1
0%
#25
1#
#30
0#
1%
b11110000 $
b11110000 (
b11110000 3
#35
b111100 "
b111100 ,
b111100 /
b111100 0
b11001100 !
b11001100 +
b11001100 -
b11110000 *
b11110000 .
b11110000 2
b11110000 4
1#
#40
b10101010 !
b10101010 +
b10101010 -
b1011010 "
b1011010 ,
b1011010 /
b1011010 0
0#
b10101010 &
b10101010 )
b10101010 1
0%
#45
1#
#50
0#
1%
b1010101 $
b1010101 (
b1010101 3
#55
b11111111 "
b11111111 ,
b11111111 /
b11111111 0
b10101010 !
b10101010 +
b10101010 -
b1010101 *
b1010101 .
b1010101 2
b1010101 4
1#
#60
b11111111 !
b11111111 +
b11111111 -
b10101010 "
b10101010 ,
b10101010 /
b10101010 0
0#
b11111111 &
b11111111 )
b11111111 1
0%
#65
1#
#70
0#
1%
b11001100 $
b11001100 (
b11001100 3
#75
b110011 "
b110011 ,
b110011 /
b110011 0
b11111111 !
b11111111 +
b11111111 -
b11001100 *
b11001100 .
b11001100 2
b11001100 4
1#
#80
b110011 !
b110011 +
b110011 -
b11111111 "
b11111111 ,
b11111111 /
b11111111 0
0#
b110011 &
b110011 )
b110011 1
0%
#85
1#
#90
0#
1%
b0 $
b0 (
b0 3
#95
b110011 "
b110011 ,
b110011 /
b110011 0
b110011 !
b110011 +
b110011 -
b0 *
b0 .
b0 2
b0 4
1#
#100
b10110110 !
b10110110 +
b10110110 -
b10110110 "
b10110110 ,
b10110110 /
b10110110 0
0#
b10110110 &
b10110110 )
b10110110 1
0%
#105
1#
#110
0#
1%
b11111111 $
b11111111 (
b11111111 3
#115
b1001001 "
b1001001 ,
b1001001 /
b1001001 0
b10110110 !
b10110110 +
b10110110 -
b11111111 *
b11111111 .
b11111111 2
b11111111 4
1#
#120
0#
0%
